gdpnum/__init__.py
gdpnum/converter.py
gdpnum/dpsgd.py
gdpnum/py.typed
gdpnum-0.1.0.dist-info/METADATA
gdpnum-0.1.0.dist-info/WHEEL
gdpnum-0.1.0.dist-info/licenses/LICENSE
gdpnum-0.1.0.dist-info/RECORD
