Metadata-Version: 2.4
Name: gdpnum
Version: 0.1.0
Summary: Numeric computation of the privacy parameter in Gaussian Differential Privacy
Author-email: Juan Felipe Gomez <juangomez@g.harvard.edu>, Bogdan Kulynych <bogdan@kulyny.ch>
License-File: LICENSE
Requires-Python: >=3.12
Requires-Dist: dp-accounting>=0.4.4
